README.md
setup.py
stylelens_detect/__init__.py
stylelens_detect/object_detect.py
stylelens_detect.egg-info/PKG-INFO
stylelens_detect.egg-info/SOURCES.txt
stylelens_detect.egg-info/dependency_links.txt
stylelens_detect.egg-info/requires.txt
stylelens_detect.egg-info/top_level.txt
stylelens_detect/grpc/__init__.py
stylelens_detect/grpc/object_detect_pb2.py
stylelens_detect/grpc/object_detect_pb2_grpc.py