Metadata-Version: 1.0
Name: stylelens-detect
Version: 1.0.3
Summary: stylelens-detect
Home-page: UNKNOWN
Author: UNKNOWN
Author-email: master@bluehack.net
License: UNKNOWN
Keywords: BlueLens,stylelens-detect
Platform: UNKNOWN
